gamma/config/__init__.py
gamma/config/__version__.py
gamma/config/builtin_tags.py
gamma/config/cache.py
gamma/config/confignode.py
gamma/config/dump_dict.py
gamma/config/dump_yaml.py
gamma/config/findconfig.py
gamma/config/globalconfig.py
gamma/config/load.py
gamma/config/merge.py
gamma/config/pydantic/__init__.py
gamma/config/rawnodes.py
gamma/config/render.py
gamma/config/render_context.py
gamma/config/sample/00-meta.yaml
gamma/config/sample/10-sample.yaml
gamma/config/sample/11-sample-override.yaml
gamma/config/sample/prod/70-sample.yaml
gamma/config/scaffold.py
gamma/config/tags.py
gamma/dispatch/__init__.py
gamma/dispatch/dispatchsystem.py
gamma/dispatch/parametric_types.py
gamma/dispatch/poset.py
gamma/dispatch/typesystem.py
gamma_config-0.8.11.dist-info/METADATA
gamma_config-0.8.11.dist-info/WHEEL
gamma_config-0.8.11.dist-info/licenses/LICENSE
gamma_config-0.8.11.dist-info/RECORD
