Metadata-Version: 2.1
Name: gamma-config
Version: 0.8.11
Summary: Config handling for data science projects
Author-Email: Cloves Almeida <cjalmeida@gmail.com>
License: MIT
Classifier: Programming Language :: Python :: 3
Classifier: Programming Language :: Python :: 3.8
Project-URL: Source, https://github.gamma.bcg.com/BCG/gamma-config/
Project-URL: Documentation, https://github.gamma.bcg.com/pages/BCG/gamma-config/
Requires-Python: >=3.8
Requires-Dist: colorama>=0.4
Requires-Dist: python-dateutil<3,>=2
Requires-Dist: python-dotenv>=0.13
Requires-Dist: ruamel.yaml>=0.16
Requires-Dist: plum-dispatch>=2.1.1
Requires-Dist: jinja2>=3; extra == "jinja2"
Requires-Dist: pydantic<3.0,>=2.0; extra == "pydantic"
Provides-Extra: jinja2
Provides-Extra: pydantic
